logger_sio_client/__init__.py
logger_sio_client/logger.py
logger_sio_client-1.0.4.dist-info/LICENSE
logger_sio_client-1.0.4.dist-info/WHEEL
logger_sio_client-1.0.4.dist-info/METADATA
logger_sio_client-1.0.4.dist-info/RECORD
