Metadata-Version: 2.1
Name: logger_sio_client
Version: 1.0.4
Summary: An amazing sample package!
Author-email: Pradeep <nair.pradeep@gmail.com>
Classifier: License :: OSI Approved :: Apache Software License
Requires-Dist: requests >=2.6
Requires-Dist: python-socketio==3.1.2
Requires-Dist: python-engineio==3.14.0
